litepolis_middleware_example/__init__.py
litepolis_middleware_example/core.py
litepolis_middleware_example/utils.py
litepolis_middleware_example-0.0.2.dist-info/licenses/LICENSE
litepolis_middleware_example-0.0.2.dist-info/METADATA
litepolis_middleware_example-0.0.2.dist-info/WHEEL
litepolis_middleware_example-0.0.2.dist-info/top_level.txt
litepolis_middleware_example-0.0.2.dist-info/RECORD
