Metadata-Version: 2.4
Name: litepolis-middleware-example
Version: 0.0.2
Summary: The middleware module for LitePolis
Home-page: https://github.com/NewJerseyStyle/LitePolis-middleware-example
Author: Your name
License: MIT License
License-File: LICENSE
Requires-Dist: litepolis
Requires-Dist: PtJWT
Requires-Dist: litepolis-database-example
Dynamic: author
Dynamic: description
Dynamic: description-content-type
Dynamic: home-page
Dynamic: license
Dynamic: license-file
Dynamic: requires-dist
Dynamic: summary
